ShenruLijieBfeFix1/README.md
ShenruLijieBfeFix1/__init__.py
ShenruLijieBfeFix1/__main__.py
ShenruLijieBfeFix1/file.epub
ShenruLijieBfeFix1/index.html
ShenruLijieBfeFix1/css/__init__.py
ShenruLijieBfeFix1/css/annotations.css
ShenruLijieBfeFix1/css/main.css
ShenruLijieBfeFix1/css/normalize.css
ShenruLijieBfeFix1/css/popup.css
ShenruLijieBfeFix1/font/__init__.py
ShenruLijieBfeFix1/font/fontello.eot
ShenruLijieBfeFix1/font/fontello.svg
ShenruLijieBfeFix1/font/fontello.ttf
ShenruLijieBfeFix1/font/fontello.woff
ShenruLijieBfeFix1/img/__init__.py
ShenruLijieBfeFix1/img/annotator-glyph-sprite.png
ShenruLijieBfeFix1/img/annotator-icon-sprite.png
ShenruLijieBfeFix1/img/apple-touch-icon.png
ShenruLijieBfeFix1/img/cancelfullscreen.png
ShenruLijieBfeFix1/img/close.png
ShenruLijieBfeFix1/img/fullscreen.png
ShenruLijieBfeFix1/img/loader.gif
ShenruLijieBfeFix1/img/menu-icon.png
ShenruLijieBfeFix1/img/save.png
ShenruLijieBfeFix1/img/saved.png
ShenruLijieBfeFix1/img/settings-s.png
ShenruLijieBfeFix1/img/settings.png
ShenruLijieBfeFix1/img/star.png
ShenruLijieBfeFix1/js/__init__.py
ShenruLijieBfeFix1/js/epub.js
ShenruLijieBfeFix1/js/epub.min.js
ShenruLijieBfeFix1/js/epub.min.map
ShenruLijieBfeFix1/js/hooks.min.js
ShenruLijieBfeFix1/js/hooks.min.map
ShenruLijieBfeFix1/js/reader.js
ShenruLijieBfeFix1/js/reader.js.map
ShenruLijieBfeFix1/js/reader.min.js
ShenruLijieBfeFix1/js/reader.min.map
ShenruLijieBfeFix1/js/hooks/__init__.py
ShenruLijieBfeFix1/js/hooks/extensions/__init__.py
ShenruLijieBfeFix1/js/hooks/extensions/highlight.js
ShenruLijieBfeFix1/js/libs/__init__.py
ShenruLijieBfeFix1/js/libs/jquery.min.js
ShenruLijieBfeFix1/js/libs/localforage.min.js
ShenruLijieBfeFix1/js/libs/screenfull.js
ShenruLijieBfeFix1/js/libs/screenfull.min.js
ShenruLijieBfeFix1/js/libs/zip.min.js
ShenruLijieBfeFix1/js/plugins/__init__.py
ShenruLijieBfeFix1/js/plugins/hypothesis.js
ShenruLijieBfeFix1/js/plugins/search.js
shenru_lijie_bfe_fix1-2025.3.25.1.dist-info/METADATA
shenru_lijie_bfe_fix1-2025.3.25.1.dist-info/WHEEL
shenru_lijie_bfe_fix1-2025.3.25.1.dist-info/entry_points.txt
shenru_lijie_bfe_fix1-2025.3.25.1.dist-info/top_level.txt
shenru_lijie_bfe_fix1-2025.3.25.1.dist-info/RECORD
